LICENSE
MANIFEST.in
README.md
setup.py
apimaticcalculatorpythonv6/__init__.py
apimaticcalculatorpythonv6/api_helper.py
apimaticcalculatorpythonv6/apimaticcalculatorpythonv6_client.py
apimaticcalculatorpythonv6/configuration.py
apimaticcalculatorpythonv6/decorators.py
apimaticcalculatorpythonv6.egg-info/PKG-INFO
apimaticcalculatorpythonv6.egg-info/SOURCES.txt
apimaticcalculatorpythonv6.egg-info/dependency_links.txt
apimaticcalculatorpythonv6.egg-info/requires.txt
apimaticcalculatorpythonv6.egg-info/top_level.txt
apimaticcalculatorpythonv6/controllers/__init__.py
apimaticcalculatorpythonv6/controllers/base_controller.py
apimaticcalculatorpythonv6/controllers/calculator_endpoints.py
apimaticcalculatorpythonv6/exceptions/__init__.py
apimaticcalculatorpythonv6/exceptions/api_exception.py
apimaticcalculatorpythonv6/http/__init__.py
apimaticcalculatorpythonv6/http/http_call_back.py
apimaticcalculatorpythonv6/http/http_client.py
apimaticcalculatorpythonv6/http/http_context.py
apimaticcalculatorpythonv6/http/http_method_enum.py
apimaticcalculatorpythonv6/http/http_request.py
apimaticcalculatorpythonv6/http/http_response.py
apimaticcalculatorpythonv6/http/requests_client.py
apimaticcalculatorpythonv6/models/__init__.py
apimaticcalculatorpythonv6/models/operation_type.py
tests/__init__.py
tests/http_response_catcher.py
tests/test_helper.py
tests/controllers/__init__.py
tests/controllers/controller_test_base.py
tests/controllers/test_calculator_endpoints.py